{
    "dataset": "Balanced-picai",
    "toShuffle": "False",
    "toTrain": "True",
    "isMultiModal": "False",
    "selected_features": "['patient_age', 'psa', 'psad', 'prostate_volume']",
    "isContrastive": "False",
    "useAI_Segmentation": "True",
    "biasFeildCorrection": "False",
    "resample": "True",
    "modalities": "['t2w']",
    "targetVoxelShape": "(1.26, 1.26, 3.78)",
    "targetimageSize": "[80, 80, 20]",
    "batchSize": "125",
    "batchAccumulator": "1",
    "percentage": "1",
    "encoder_emb_sz": "100",
    "augmentation": "<function augmentation_supervised at 0x7f62ae799820>",
    "table_corruption": "0.3",
    "encoder_weights_path": "/u/home/seel/ADLM/adlm_ss2023_mmcl/results/picai/picai_Multmodal_Contrastive_lasso_morph_ResNet10_500e/encoder.pt",
    "encoder": "<class 'models.encoders.Contrastive_Encoder_resnet10'>",
    "tabular_encoder": "<class 'models.encoders.Tabular_Encoder'>",
    "encoder_optim": "<class 'torch.optim.adam.Adam'>",
    "encoder_lr": "0.0002",
    "embClassifer": "None",
    "loss": "BCELoss()",
    "epochs": "100"
}